spgrep_modulation/__init__.py
spgrep_modulation/irreps.py
spgrep_modulation/isotropy.py
spgrep_modulation/modulation.py
spgrep_modulation/utils.py
spgrep_modulation/visualize.py
spgrep_modulation-0.2.7.dist-info/licenses/LICENSE
spgrep_modulation-0.2.7.dist-info/METADATA
spgrep_modulation-0.2.7.dist-info/WHEEL
spgrep_modulation-0.2.7.dist-info/top_level.txt
spgrep_modulation-0.2.7.dist-info/RECORD
