Metadata-Version: 2.4
Name: spgrep_modulation
Version: 0.2.7
Summary: Collective atomic modulation analysis with irreducible space-group representation
Author-email: Kohei Shinohara <kshinohara0508@gmail.com>
License: BSD 3-Clause License
Project-URL: repository, https://github.com/lan496/spgrep-modulation
Project-URL: homepage, https://phonopy.github.io/spgrep-modulation
Project-URL: documentation, https://phonopy.github.io/spgrep-modulation
Project-URL: changelog, https://phonopy.github.io/spgrep-modulation/changelog.html
Classifier: Development Status :: 2 - Pre-Alpha
Classifier: Intended Audience :: Science/Research
Classifier: License :: OSI Approved :: BSD License
Classifier: Operating System :: OS Independent
Classifier: Programming Language :: Python
Classifier: Programming Language :: Python :: 3.9
Classifier: Programming Language :: Python :: 3.10
Classifier: Programming Language :: Python :: 3.11
Classifier: Programming Language :: Python :: 3.12
Classifier: Topic :: Scientific/Engineering :: Physics
Requires-Python: >=3.9.0
License-File: LICENSE
Requires-Dist: setuptools
Requires-Dist: setuptools_scm
Requires-Dist: wheel
Requires-Dist: typing_extensions
Requires-Dist: numpy>=1.20.1
Requires-Dist: spglib>=2.0.2
Requires-Dist: phonopy>=2.15.1
Requires-Dist: seekpath
Requires-Dist: spgrep>=0.3.3
Requires-Dist: hsnf>=0.3.15
Provides-Extra: vis
Requires-Dist: ipykernel; extra == "vis"
Requires-Dist: notebook>=4.2; extra == "vis"
Requires-Dist: ipywidgets; extra == "vis"
Requires-Dist: nglview>=3.0.4; extra == "vis"
Requires-Dist: ase>=3.23; extra == "vis"
Requires-Dist: pymatgen>=2022.8.23; extra == "vis"
Provides-Extra: dev
Requires-Dist: pytest; extra == "dev"
Requires-Dist: pytest-cov; extra == "dev"
Requires-Dist: pre-commit; extra == "dev"
Requires-Dist: black; extra == "dev"
Requires-Dist: mypy; extra == "dev"
Requires-Dist: flake8; extra == "dev"
Requires-Dist: pyupgrade; extra == "dev"
Requires-Dist: ipython; extra == "dev"
Requires-Dist: click; extra == "dev"
Requires-Dist: networkx; extra == "dev"
Provides-Extra: docs
Requires-Dist: docutils>=0.20; extra == "docs"
Requires-Dist: sphinx; extra == "docs"
Requires-Dist: sphinx-autobuild; extra == "docs"
Requires-Dist: nbsphinx; extra == "docs"
Requires-Dist: sphinxcontrib-bibtex; extra == "docs"
Requires-Dist: myst-parser; extra == "docs"
Requires-Dist: sphinx-book-theme; extra == "docs"
Dynamic: license-file
